[
  {
    "time": "2026-03-01T20:19:01Z",
    "category": "system",
    "message": "scraper-reddit: STOPPED"
  },
  {
    "time": "2026-03-01T20:19:01Z",
    "category": "system",
    "message": "scraper-sources: running"
  },
  {
    "time": "2026-03-01T20:19:01Z",
    "category": "system",
    "message": "ingest: running"
  },
  {
    "time": "2026-03-01T20:19:01Z",
    "category": "infrastructure",
    "message": "Container biddings-postgres Up 37 hours (healthy)"
  },
  {
    "time": "2026-03-01T20:19:01Z",
    "category": "infrastructure",
    "message": "Container biddings-qdrant Up 46 hours"
  },
  {
    "time": "2026-03-01T20:19:01Z",
    "category": "infrastructure",
    "message": "Container biddings-neo4j Up 46 hours (healthy)"
  },
  {
    "time": "2026-03-01T20:19:01Z",
    "category": "infrastructure",
    "message": "Container qdrant Up 2 days"
  },
  {
    "time": "2026-03-01T20:19:01Z",
    "category": "infrastructure",
    "message": "Container neo4j Up 2 days"
  },
  {
    "time": "2026-03-01T20:19:01Z",
    "category": "system",
    "message": "Data directory: 322M\t/tmp/wessley-data"
  },
  {
    "time": "2026-03-01T20:15:59Z",
    "category": "ingestion",
    "message": "File ifixit-1772396159055448000.json (4KB) processed"
  },
  {
    "time": "2026-03-01T20:15:51Z",
    "category": "ingestion",
    "message": "File nhtsa-1772396151836600000.json (409KB) processed"
  },
  {
    "time": "2026-03-01T20:03:40Z",
    "category": "ingestion",
    "message": "File ifixit-1772395420937828000.json (4KB) processed"
  },
  {
    "time": "2026-03-01T20:03:33Z",
    "category": "ingestion",
    "message": "File nhtsa-1772395413715326000.json (379KB) processed"
  },
  {
    "time": "2026-03-01T20:03:29Z",
    "category": "ingestion",
    "message": "File ifixit-1772395409834525000.json (4KB) processed"
  },
  {
    "time": "2026-03-01T20:03:22Z",
    "category": "ingestion",
    "message": "File nhtsa-1772395402614529000.json (392KB) processed"
  },
  {
    "time": "2026-03-01T20:01:45Z",
    "category": "ingestion",
    "message": "File sources-2026-03-01-archive.json (80536KB) processed"
  },
  {
    "time": "2026-03-01T19:45:59Z",
    "category": "ingestion",
    "message": "File ifixit-1772394359873468000.json (4KB) processed"
  },
  {
    "time": "2026-03-01T19:45:51Z",
    "category": "ingestion",
    "message": "File nhtsa-1772394351789531000.json (409KB) processed"
  },
  {
    "time": "2026-03-01T19:33:30Z",
    "category": "ingestion",
    "message": "File ifixit-1772393610592805000.json (4KB) processed"
  }
]